<?xml version='1.0' encoding='utf-8'?>
<tv generator-info-name="fonseware jellyfin" source-info-name="fonseware-cable">
  <channel id="001">
    <display-name>Cable TV</display-name>
    <icon src="http://cable.fnswe.me/res/fw-cable-light.png" />
  </channel>
  <channel id="002">
    <display-name>FBS teve</display-name>
    <icon src="http://cable.fnswe.me/media/fw-teve-logo2-light.png" />
  </channel>
  <channel id="003">
    <display-name>No TV channel</display-name>
    <icon src="http://cable.fnswe.me/media/fw-cable-nochannel.png" />
  </channel>
  <programme start="20260328000000 +0000" stop="20260329000000 +0000" channel="001">
    <title lang="en">No programme set</title>
    <desc lang="en">Cable TV has not set a programme block yet. Right now you are seeing a placeholder block. Please wait while we or the broadcaster settle this.</desc>
    <category lang="en">General</category>
    <date>2026</date>
    <icon src="http://cable.fnswe.me/media/placeholder3.jpg" />
    <episode-num system="xmltv_ns">0.0.0/1</episode-num>
  </programme>
  <programme start="20260328000000 +0000" stop="20260328003000 +0000" channel="002">
    <title lang="en">No programme set</title>
    <desc lang="en">FBS teve has not set a programme block yet. Right now you are seeing a placeholder block. Please wait while we or the broadcaster settle this.</desc>
    <category lang="en">General</category>
    <date>2026</date>
    <icon src="http://cable.fnswe.me/media/placeholder2.jpg" />
    <episode-num system="xmltv_ns">0.0.0/1</episode-num>
  </programme>
  <programme start="20260328003000 +0000" stop="20260328010000 +0000" channel="002">
    <title lang="en">No programme set</title>
    <desc lang="en">FBS teve has not set a programme block yet. Right now you are seeing a placeholder block. Please wait while we or the broadcaster settle this.</desc>
    <category lang="en">General</category>
    <date>2026</date>
    <icon src="http://cable.fnswe.me/media/placeholder2.jpg" />
    <episode-num system="xmltv_ns">0.0.0/1</episode-num>
  </programme>
  <programme start="20260328010000 +0000" stop="20260328013000 +0000" channel="002">
    <title lang="en">No programme set</title>
    <desc lang="en">FBS teve has not set a programme block yet. Right now you are seeing a placeholder block. Please wait while we or the broadcaster settle this.</desc>
    <category lang="en">General</category>
    <date>2026</date>
    <icon src="http://cable.fnswe.me/media/placeholder2.jpg" />
    <episode-num system="xmltv_ns">0.0.0/1</episode-num>
  </programme>
  <programme start="20260328013000 +0000" stop="20260328020000 +0000" channel="002">
    <title lang="en">No programme set</title>
    <desc lang="en">FBS teve has not set a programme block yet. Right now you are seeing a placeholder block. Please wait while we or the broadcaster settle this.</desc>
    <category lang="en">General</category>
    <date>2026</date>
    <icon src="http://cable.fnswe.me/media/placeholder2.jpg" />
    <episode-num system="xmltv_ns">0.0.0/1</episode-num>
  </programme>
  <programme start="20260328020000 +0000" stop="20260328023000 +0000" channel="002">
    <title lang="en">No programme set</title>
    <desc lang="en">FBS teve has not set a programme block yet. Right now you are seeing a placeholder block. Please wait while we or the broadcaster settle this.</desc>
    <category lang="en">General</category>
    <date>2026</date>
    <icon src="http://cable.fnswe.me/media/placeholder3.jpg" />
    <episode-num system="xmltv_ns">0.0.0/1</episode-num>
  </programme>
  <programme start="20260328023000 +0000" stop="20260328030000 +0000" channel="002">
    <title lang="en">No programme set</title>
    <desc lang="en">FBS teve has not set a programme block yet. Right now you are seeing a placeholder block. Please wait while we or the broadcaster settle this.</desc>
    <category lang="en">General</category>
    <date>2026</date>
    <icon src="http://cable.fnswe.me/media/placeholder2.jpg" />
    <episode-num system="xmltv_ns">0.0.0/1</episode-num>
  </programme>
  <programme start="20260328030000 +0000" stop="20260328033000 +0000" channel="002">
    <title lang="en">No programme set</title>
    <desc lang="en">FBS teve has not set a programme block yet. Right now you are seeing a placeholder block. Please wait while we or the broadcaster settle this.</desc>
    <category lang="en">General</category>
    <date>2026</date>
    <icon src="http://cable.fnswe.me/media/placeholder2.jpg" />
    <episode-num system="xmltv_ns">0.0.0/1</episode-num>
  </programme>
  <programme start="20260328033000 +0000" stop="20260328040000 +0000" channel="002">
    <title lang="en">No programme set</title>
    <desc lang="en">FBS teve has not set a programme block yet. Right now you are seeing a placeholder block. Please wait while we or the broadcaster settle this.</desc>
    <category lang="en">General</category>
    <date>2026</date>
    <icon src="http://cable.fnswe.me/media/placeholder2.jpg" />
    <episode-num system="xmltv_ns">0.0.0/1</episode-num>
  </programme>
  <programme start="20260328040000 +0000" stop="20260328043000 +0000" channel="002">
    <title lang="en">No programme set</title>
    <desc lang="en">FBS teve has not set a programme block yet. Right now you are seeing a placeholder block. Please wait while we or the broadcaster settle this.</desc>
    <category lang="en">General</category>
    <date>2026</date>
    <icon src="http://cable.fnswe.me/media/placeholder2.jpg" />
    <episode-num system="xmltv_ns">0.0.0/1</episode-num>
  </programme>
  <programme start="20260328043000 +0000" stop="20260328050000 +0000" channel="002">
    <title lang="en">No programme set</title>
    <desc lang="en">FBS teve has not set a programme block yet. Right now you are seeing a placeholder block. Please wait while we or the broadcaster settle this.</desc>
    <category lang="en">General</category>
    <date>2026</date>
    <icon src="http://cable.fnswe.me/media/placeholder2.jpg" />
    <episode-num system="xmltv_ns">0.0.0/1</episode-num>
  </programme>
  <programme start="20260328050000 +0000" stop="20260328053000 +0000" channel="002">
    <title lang="en">No programme set</title>
    <desc lang="en">FBS teve has not set a programme block yet. Right now you are seeing a placeholder block. Please wait while we or the broadcaster settle this.</desc>
    <category lang="en">General</category>
    <date>2026</date>
    <icon src="http://cable.fnswe.me/media/placeholder2.jpg" />
    <episode-num system="xmltv_ns">0.0.0/1</episode-num>
  </programme>
  <programme start="20260328053000 +0000" stop="20260328060000 +0000" channel="002">
    <title lang="en">No programme set</title>
    <desc lang="en">FBS teve has not set a programme block yet. Right now you are seeing a placeholder block. Please wait while we or the broadcaster settle this.</desc>
    <category lang="en">General</category>
    <date>2026</date>
    <icon src="http://cable.fnswe.me/media/placeholder2.jpg" />
    <episode-num system="xmltv_ns">0.0.0/1</episode-num>
  </programme>
  <programme start="20260328060000 +0000" stop="20260328063000 +0000" channel="002">
    <title lang="en">No programme set</title>
    <desc lang="en">FBS teve has not set a programme block yet. Right now you are seeing a placeholder block. Please wait while we or the broadcaster settle this.</desc>
    <category lang="en">General</category>
    <date>2026</date>
    <icon src="http://cable.fnswe.me/media/placeholder3.jpg" />
    <episode-num system="xmltv_ns">0.0.0/1</episode-num>
  </programme>
  <programme start="20260328063000 +0000" stop="20260328070000 +0000" channel="002">
    <title lang="en">No programme set</title>
    <desc lang="en">FBS teve has not set a programme block yet. Right now you are seeing a placeholder block. Please wait while we or the broadcaster settle this.</desc>
    <category lang="en">General</category>
    <date>2026</date>
    <icon src="http://cable.fnswe.me/media/placeholder2.jpg" />
    <episode-num system="xmltv_ns">0.0.0/1</episode-num>
  </programme>
  <programme start="20260328070000 +0000" stop="20260328073000 +0000" channel="002">
    <title lang="en">No programme set</title>
    <desc lang="en">FBS teve has not set a programme block yet. Right now you are seeing a placeholder block. Please wait while we or the broadcaster settle this.</desc>
    <category lang="en">General</category>
    <date>2026</date>
    <icon src="http://cable.fnswe.me/media/placeholder2.jpg" />
    <episode-num system="xmltv_ns">0.0.0/1</episode-num>
  </programme>
  <programme start="20260328073000 +0000" stop="20260328080000 +0000" channel="002">
    <title lang="en">No programme set</title>
    <desc lang="en">FBS teve has not set a programme block yet. Right now you are seeing a placeholder block. Please wait while we or the broadcaster settle this.</desc>
    <category lang="en">General</category>
    <date>2026</date>
    <icon src="http://cable.fnswe.me/media/placeholder3.jpg" />
    <episode-num system="xmltv_ns">0.0.0/1</episode-num>
  </programme>
  <programme start="20260328080000 +0000" stop="20260328083000 +0000" channel="002">
    <title lang="en">No programme set</title>
    <desc lang="en">FBS teve has not set a programme block yet. Right now you are seeing a placeholder block. Please wait while we or the broadcaster settle this.</desc>
    <category lang="en">General</category>
    <date>2026</date>
    <icon src="http://cable.fnswe.me/media/placeholder3.jpg" />
    <episode-num system="xmltv_ns">0.0.0/1</episode-num>
  </programme>
  <programme start="20260328083000 +0000" stop="20260328090000 +0000" channel="002">
    <title lang="en">No programme set</title>
    <desc lang="en">FBS teve has not set a programme block yet. Right now you are seeing a placeholder block. Please wait while we or the broadcaster settle this.</desc>
    <category lang="en">General</category>
    <date>2026</date>
    <icon src="http://cable.fnswe.me/media/placeholder2.jpg" />
    <episode-num system="xmltv_ns">0.0.0/1</episode-num>
  </programme>
  <programme start="20260328090000 +0000" stop="20260328093000 +0000" channel="002">
    <title lang="en">No programme set</title>
    <desc lang="en">FBS teve has not set a programme block yet. Right now you are seeing a placeholder block. Please wait while we or the broadcaster settle this.</desc>
    <category lang="en">General</category>
    <date>2026</date>
    <icon src="http://cable.fnswe.me/media/placeholder2.jpg" />
    <episode-num system="xmltv_ns">0.0.0/1</episode-num>
  </programme>
  <programme start="20260328093000 +0000" stop="20260328100000 +0000" channel="002">
    <title lang="en">No programme set</title>
    <desc lang="en">FBS teve has not set a programme block yet. Right now you are seeing a placeholder block. Please wait while we or the broadcaster settle this.</desc>
    <category lang="en">General</category>
    <date>2026</date>
    <icon src="http://cable.fnswe.me/media/placeholder3.jpg" />
    <episode-num system="xmltv_ns">0.0.0/1</episode-num>
  </programme>
  <programme start="20260328100000 +0000" stop="20260328103000 +0000" channel="002">
    <title lang="en">No programme set</title>
    <desc lang="en">FBS teve has not set a programme block yet. Right now you are seeing a placeholder block. Please wait while we or the broadcaster settle this.</desc>
    <category lang="en">General</category>
    <date>2026</date>
    <icon src="http://cable.fnswe.me/media/placeholder1.jpg" />
    <episode-num system="xmltv_ns">0.0.0/1</episode-num>
  </programme>
  <programme start="20260328103000 +0000" stop="20260328110000 +0000" channel="002">
    <title lang="en">No programme set</title>
    <desc lang="en">FBS teve has not set a programme block yet. Right now you are seeing a placeholder block. Please wait while we or the broadcaster settle this.</desc>
    <category lang="en">General</category>
    <date>2026</date>
    <icon src="http://cable.fnswe.me/media/placeholder3.jpg" />
    <episode-num system="xmltv_ns">0.0.0/1</episode-num>
  </programme>
  <programme start="20260328110000 +0000" stop="20260328113000 +0000" channel="002">
    <title lang="en">No programme set</title>
    <desc lang="en">FBS teve has not set a programme block yet. Right now you are seeing a placeholder block. Please wait while we or the broadcaster settle this.</desc>
    <category lang="en">General</category>
    <date>2026</date>
    <icon src="http://cable.fnswe.me/media/placeholder3.jpg" />
    <episode-num system="xmltv_ns">0.0.0/1</episode-num>
  </programme>
  <programme start="20260328113000 +0000" stop="20260328120000 +0000" channel="002">
    <title lang="en">No programme set</title>
    <desc lang="en">FBS teve has not set a programme block yet. Right now you are seeing a placeholder block. Please wait while we or the broadcaster settle this.</desc>
    <category lang="en">General</category>
    <date>2026</date>
    <icon src="http://cable.fnswe.me/media/placeholder2.jpg" />
    <episode-num system="xmltv_ns">0.0.0/1</episode-num>
  </programme>
  <programme start="20260328120000 +0000" stop="20260328123000 +0000" channel="002">
    <title lang="en">No programme set</title>
    <desc lang="en">FBS teve has not set a programme block yet. Right now you are seeing a placeholder block. Please wait while we or the broadcaster settle this.</desc>
    <category lang="en">General</category>
    <date>2026</date>
    <icon src="http://cable.fnswe.me/media/placeholder3.jpg" />
    <episode-num system="xmltv_ns">0.0.0/1</episode-num>
  </programme>
  <programme start="20260328123000 +0000" stop="20260328130000 +0000" channel="002">
    <title lang="en">No programme set</title>
    <desc lang="en">FBS teve has not set a programme block yet. Right now you are seeing a placeholder block. Please wait while we or the broadcaster settle this.</desc>
    <category lang="en">General</category>
    <date>2026</date>
    <icon src="http://cable.fnswe.me/media/placeholder2.jpg" />
    <episode-num system="xmltv_ns">0.0.0/1</episode-num>
  </programme>
  <programme start="20260328130000 +0000" stop="20260328133000 +0000" channel="002">
    <title lang="en">No programme set</title>
    <desc lang="en">FBS teve has not set a programme block yet. Right now you are seeing a placeholder block. Please wait while we or the broadcaster settle this.</desc>
    <category lang="en">General</category>
    <date>2026</date>
    <icon src="http://cable.fnswe.me/media/placeholder3.jpg" />
    <episode-num system="xmltv_ns">0.0.0/1</episode-num>
  </programme>
  <programme start="20260328133000 +0000" stop="20260328140000 +0000" channel="002">
    <title lang="en">No programme set</title>
    <desc lang="en">FBS teve has not set a programme block yet. Right now you are seeing a placeholder block. Please wait while we or the broadcaster settle this.</desc>
    <category lang="en">General</category>
    <date>2026</date>
    <icon src="http://cable.fnswe.me/media/placeholder3.jpg" />
    <episode-num system="xmltv_ns">0.0.0/1</episode-num>
  </programme>
  <programme start="20260328140000 +0000" stop="20260328143000 +0000" channel="002">
    <title lang="en">No programme set</title>
    <desc lang="en">FBS teve has not set a programme block yet. Right now you are seeing a placeholder block. Please wait while we or the broadcaster settle this.</desc>
    <category lang="en">General</category>
    <date>2026</date>
    <icon src="http://cable.fnswe.me/media/placeholder3.jpg" />
    <episode-num system="xmltv_ns">0.0.0/1</episode-num>
  </programme>
  <programme start="20260328143000 +0000" stop="20260328150000 +0000" channel="002">
    <title lang="en">No programme set</title>
    <desc lang="en">FBS teve has not set a programme block yet. Right now you are seeing a placeholder block. Please wait while we or the broadcaster settle this.</desc>
    <category lang="en">General</category>
    <date>2026</date>
    <icon src="http://cable.fnswe.me/media/placeholder1.jpg" />
    <episode-num system="xmltv_ns">0.0.0/1</episode-num>
  </programme>
  <programme start="20260328150000 +0000" stop="20260328153000 +0000" channel="002">
    <title lang="en">No programme set</title>
    <desc lang="en">FBS teve has not set a programme block yet. Right now you are seeing a placeholder block. Please wait while we or the broadcaster settle this.</desc>
    <category lang="en">General</category>
    <date>2026</date>
    <icon src="http://cable.fnswe.me/media/placeholder2.jpg" />
    <episode-num system="xmltv_ns">0.0.0/1</episode-num>
  </programme>
  <programme start="20260328153000 +0000" stop="20260328160000 +0000" channel="002">
    <title lang="en">No programme set</title>
    <desc lang="en">FBS teve has not set a programme block yet. Right now you are seeing a placeholder block. Please wait while we or the broadcaster settle this.</desc>
    <category lang="en">General</category>
    <date>2026</date>
    <icon src="http://cable.fnswe.me/media/placeholder1.jpg" />
    <episode-num system="xmltv_ns">0.0.0/1</episode-num>
  </programme>
  <programme start="20260328160000 +0000" stop="20260328163000 +0000" channel="002">
    <title lang="en">No programme set</title>
    <desc lang="en">FBS teve has not set a programme block yet. Right now you are seeing a placeholder block. Please wait while we or the broadcaster settle this.</desc>
    <category lang="en">General</category>
    <date>2026</date>
    <icon src="http://cable.fnswe.me/media/placeholder2.jpg" />
    <episode-num system="xmltv_ns">0.0.0/1</episode-num>
  </programme>
  <programme start="20260328163000 +0000" stop="20260328170000 +0000" channel="002">
    <title lang="en">No programme set</title>
    <desc lang="en">FBS teve has not set a programme block yet. Right now you are seeing a placeholder block. Please wait while we or the broadcaster settle this.</desc>
    <category lang="en">General</category>
    <date>2026</date>
    <icon src="http://cable.fnswe.me/media/placeholder1.jpg" />
    <episode-num system="xmltv_ns">0.0.0/1</episode-num>
  </programme>
  <programme start="20260328170000 +0000" stop="20260328173000 +0000" channel="002">
    <title lang="en">No programme set</title>
    <desc lang="en">FBS teve has not set a programme block yet. Right now you are seeing a placeholder block. Please wait while we or the broadcaster settle this.</desc>
    <category lang="en">General</category>
    <date>2026</date>
    <icon src="http://cable.fnswe.me/media/placeholder3.jpg" />
    <episode-num system="xmltv_ns">0.0.0/1</episode-num>
  </programme>
  <programme start="20260328173000 +0000" stop="20260328180000 +0000" channel="002">
    <title lang="en">No programme set</title>
    <desc lang="en">FBS teve has not set a programme block yet. Right now you are seeing a placeholder block. Please wait while we or the broadcaster settle this.</desc>
    <category lang="en">General</category>
    <date>2026</date>
    <icon src="http://cable.fnswe.me/media/placeholder1.jpg" />
    <episode-num system="xmltv_ns">0.0.0/1</episode-num>
  </programme>
  <programme start="20260328180000 +0000" stop="20260328183000 +0000" channel="002">
    <title lang="en">No programme set</title>
    <desc lang="en">FBS teve has not set a programme block yet. Right now you are seeing a placeholder block. Please wait while we or the broadcaster settle this.</desc>
    <category lang="en">General</category>
    <date>2026</date>
    <icon src="http://cable.fnswe.me/media/placeholder3.jpg" />
    <episode-num system="xmltv_ns">0.0.0/1</episode-num>
  </programme>
  <programme start="20260328183000 +0000" stop="20260328190000 +0000" channel="002">
    <title lang="en">No programme set</title>
    <desc lang="en">FBS teve has not set a programme block yet. Right now you are seeing a placeholder block. Please wait while we or the broadcaster settle this.</desc>
    <category lang="en">General</category>
    <date>2026</date>
    <icon src="http://cable.fnswe.me/media/placeholder3.jpg" />
    <episode-num system="xmltv_ns">0.0.0/1</episode-num>
  </programme>
  <programme start="20260328190000 +0000" stop="20260328193000 +0000" channel="002">
    <title lang="en">No programme set</title>
    <desc lang="en">FBS teve has not set a programme block yet. Right now you are seeing a placeholder block. Please wait while we or the broadcaster settle this.</desc>
    <category lang="en">General</category>
    <date>2026</date>
    <icon src="http://cable.fnswe.me/media/placeholder1.jpg" />
    <episode-num system="xmltv_ns">0.0.0/1</episode-num>
  </programme>
  <programme start="20260328193000 +0000" stop="20260328200000 +0000" channel="002">
    <title lang="en">No programme set</title>
    <desc lang="en">FBS teve has not set a programme block yet. Right now you are seeing a placeholder block. Please wait while we or the broadcaster settle this.</desc>
    <category lang="en">General</category>
    <date>2026</date>
    <icon src="http://cable.fnswe.me/media/placeholder2.jpg" />
    <episode-num system="xmltv_ns">0.0.0/1</episode-num>
  </programme>
  <programme start="20260328200000 +0000" stop="20260328203000 +0000" channel="002">
    <title lang="en">No programme set</title>
    <desc lang="en">FBS teve has not set a programme block yet. Right now you are seeing a placeholder block. Please wait while we or the broadcaster settle this.</desc>
    <category lang="en">General</category>
    <date>2026</date>
    <icon src="http://cable.fnswe.me/media/placeholder1.jpg" />
    <episode-num system="xmltv_ns">0.0.0/1</episode-num>
  </programme>
  <programme start="20260328203000 +0000" stop="20260328210000 +0000" channel="002">
    <title lang="en">No programme set</title>
    <desc lang="en">FBS teve has not set a programme block yet. Right now you are seeing a placeholder block. Please wait while we or the broadcaster settle this.</desc>
    <category lang="en">General</category>
    <date>2026</date>
    <icon src="http://cable.fnswe.me/media/placeholder2.jpg" />
    <episode-num system="xmltv_ns">0.0.0/1</episode-num>
  </programme>
  <programme start="20260328210000 +0000" stop="20260328213000 +0000" channel="002">
    <title lang="en">No programme set</title>
    <desc lang="en">FBS teve has not set a programme block yet. Right now you are seeing a placeholder block. Please wait while we or the broadcaster settle this.</desc>
    <category lang="en">General</category>
    <date>2026</date>
    <icon src="http://cable.fnswe.me/media/placeholder2.jpg" />
    <episode-num system="xmltv_ns">0.0.0/1</episode-num>
  </programme>
  <programme start="20260328213000 +0000" stop="20260328220000 +0000" channel="002">
    <title lang="en">No programme set</title>
    <desc lang="en">FBS teve has not set a programme block yet. Right now you are seeing a placeholder block. Please wait while we or the broadcaster settle this.</desc>
    <category lang="en">General</category>
    <date>2026</date>
    <icon src="http://cable.fnswe.me/media/placeholder2.jpg" />
    <episode-num system="xmltv_ns">0.0.0/1</episode-num>
  </programme>
  <programme start="20260328220000 +0000" stop="20260328223000 +0000" channel="002">
    <title lang="en">No programme set</title>
    <desc lang="en">FBS teve has not set a programme block yet. Right now you are seeing a placeholder block. Please wait while we or the broadcaster settle this.</desc>
    <category lang="en">General</category>
    <date>2026</date>
    <icon src="http://cable.fnswe.me/media/placeholder1.jpg" />
    <episode-num system="xmltv_ns">0.0.0/1</episode-num>
  </programme>
  <programme start="20260328223000 +0000" stop="20260328230000 +0000" channel="002">
    <title lang="en">No programme set</title>
    <desc lang="en">FBS teve has not set a programme block yet. Right now you are seeing a placeholder block. Please wait while we or the broadcaster settle this.</desc>
    <category lang="en">General</category>
    <date>2026</date>
    <icon src="http://cable.fnswe.me/media/placeholder1.jpg" />
    <episode-num system="xmltv_ns">0.0.0/1</episode-num>
  </programme>
  <programme start="20260328230000 +0000" stop="20260328233000 +0000" channel="002">
    <title lang="en">No programme set</title>
    <desc lang="en">FBS teve has not set a programme block yet. Right now you are seeing a placeholder block. Please wait while we or the broadcaster settle this.</desc>
    <category lang="en">General</category>
    <date>2026</date>
    <icon src="http://cable.fnswe.me/media/placeholder2.jpg" />
    <episode-num system="xmltv_ns">0.0.0/1</episode-num>
  </programme>
  <programme start="20260328233000 +0000" stop="20260329000000 +0000" channel="002">
    <title lang="en">No programme set</title>
    <desc lang="en">FBS teve has not set a programme block yet. Right now you are seeing a placeholder block. Please wait while we or the broadcaster settle this.</desc>
    <category lang="en">General</category>
    <date>2026</date>
    <icon src="http://cable.fnswe.me/media/placeholder1.jpg" />
    <episode-num system="xmltv_ns">0.0.0/1</episode-num>
  </programme>
  <programme start="20260328000000 +0000" stop="20260329000000 +0000" channel="003">
    <title lang="en">No programme set</title>
    <desc lang="en">No TV channel has not set a programme block yet. Right now you are seeing a placeholder block. Please wait while we or the broadcaster settle this.</desc>
    <category lang="en">General</category>
    <date>2026</date>
    <icon src="http://cable.fnswe.me/media/placeholder2.jpg" />
    <episode-num system="xmltv_ns">0.0.0/1</episode-num>
  </programme>
</tv>