<?xml version='1.0' encoding='utf-8'?>
<tv generator-info-name="fonseware jellyfin" source-info-name="fonseware-cable">
  <channel id="001">
    <display-name>Cable TV</display-name>
    <icon src="http://cable.fnswe.me/res/fw-cable-light.png" />
  </channel>
  <channel id="002">
    <display-name>FBS teve</display-name>
    <icon src="http://cable.fnswe.me/media/fw-teve-logo2-light.png" />
  </channel>
  <channel id="003">
    <display-name>No TV channel</display-name>
    <icon src="http://cable.fnswe.me/media/fw-cable-nochannel.png" />
  </channel>
  <programme start="20260410000000 +0000" stop="20260411000000 +0000" channel="001">
    <title lang="en">No programme set</title>
    <desc lang="en">Cable TV has not set a programme block yet. Right now you are seeing a placeholder block. Please wait while we or the broadcaster settle this.</desc>
    <category lang="en">General</category>
    <date>2026</date>
    <icon src="http://cable.fnswe.me/media/placeholder3.jpg" />
    <episode-num system="xmltv_ns">0.0.0/1</episode-num>
  </programme>
  <programme start="20260410000000 +0000" stop="20260410003000 +0000" channel="002">
    <title lang="en">No programme set</title>
    <desc lang="en">FBS teve has not set a programme block yet. Right now you are seeing a placeholder block. Please wait while we or the broadcaster settle this.</desc>
    <category lang="en">General</category>
    <date>2026</date>
    <icon src="http://cable.fnswe.me/media/placeholder2.jpg" />
    <episode-num system="xmltv_ns">0.0.0/1</episode-num>
  </programme>
  <programme start="20260410003000 +0000" stop="20260410010000 +0000" channel="002">
    <title lang="en">No programme set</title>
    <desc lang="en">FBS teve has not set a programme block yet. Right now you are seeing a placeholder block. Please wait while we or the broadcaster settle this.</desc>
    <category lang="en">General</category>
    <date>2026</date>
    <icon src="http://cable.fnswe.me/media/placeholder1.jpg" />
    <episode-num system="xmltv_ns">0.0.0/1</episode-num>
  </programme>
  <programme start="20260410010000 +0000" stop="20260410013000 +0000" channel="002">
    <title lang="en">No programme set</title>
    <desc lang="en">FBS teve has not set a programme block yet. Right now you are seeing a placeholder block. Please wait while we or the broadcaster settle this.</desc>
    <category lang="en">General</category>
    <date>2026</date>
    <icon src="http://cable.fnswe.me/media/placeholder2.jpg" />
    <episode-num system="xmltv_ns">0.0.0/1</episode-num>
  </programme>
  <programme start="20260410013000 +0000" stop="20260410020000 +0000" channel="002">
    <title lang="en">No programme set</title>
    <desc lang="en">FBS teve has not set a programme block yet. Right now you are seeing a placeholder block. Please wait while we or the broadcaster settle this.</desc>
    <category lang="en">General</category>
    <date>2026</date>
    <icon src="http://cable.fnswe.me/media/placeholder3.jpg" />
    <episode-num system="xmltv_ns">0.0.0/1</episode-num>
  </programme>
  <programme start="20260410020000 +0000" stop="20260410023000 +0000" channel="002">
    <title lang="en">No programme set</title>
    <desc lang="en">FBS teve has not set a programme block yet. Right now you are seeing a placeholder block. Please wait while we or the broadcaster settle this.</desc>
    <category lang="en">General</category>
    <date>2026</date>
    <icon src="http://cable.fnswe.me/media/placeholder3.jpg" />
    <episode-num system="xmltv_ns">0.0.0/1</episode-num>
  </programme>
  <programme start="20260410023000 +0000" stop="20260410030000 +0000" channel="002">
    <title lang="en">No programme set</title>
    <desc lang="en">FBS teve has not set a programme block yet. Right now you are seeing a placeholder block. Please wait while we or the broadcaster settle this.</desc>
    <category lang="en">General</category>
    <date>2026</date>
    <icon src="http://cable.fnswe.me/media/placeholder1.jpg" />
    <episode-num system="xmltv_ns">0.0.0/1</episode-num>
  </programme>
  <programme start="20260410030000 +0000" stop="20260410033000 +0000" channel="002">
    <title lang="en">No programme set</title>
    <desc lang="en">FBS teve has not set a programme block yet. Right now you are seeing a placeholder block. Please wait while we or the broadcaster settle this.</desc>
    <category lang="en">General</category>
    <date>2026</date>
    <icon src="http://cable.fnswe.me/media/placeholder3.jpg" />
    <episode-num system="xmltv_ns">0.0.0/1</episode-num>
  </programme>
  <programme start="20260410033000 +0000" stop="20260410040000 +0000" channel="002">
    <title lang="en">No programme set</title>
    <desc lang="en">FBS teve has not set a programme block yet. Right now you are seeing a placeholder block. Please wait while we or the broadcaster settle this.</desc>
    <category lang="en">General</category>
    <date>2026</date>
    <icon src="http://cable.fnswe.me/media/placeholder1.jpg" />
    <episode-num system="xmltv_ns">0.0.0/1</episode-num>
  </programme>
  <programme start="20260410040000 +0000" stop="20260410043000 +0000" channel="002">
    <title lang="en">No programme set</title>
    <desc lang="en">FBS teve has not set a programme block yet. Right now you are seeing a placeholder block. Please wait while we or the broadcaster settle this.</desc>
    <category lang="en">General</category>
    <date>2026</date>
    <icon src="http://cable.fnswe.me/media/placeholder2.jpg" />
    <episode-num system="xmltv_ns">0.0.0/1</episode-num>
  </programme>
  <programme start="20260410043000 +0000" stop="20260410050000 +0000" channel="002">
    <title lang="en">No programme set</title>
    <desc lang="en">FBS teve has not set a programme block yet. Right now you are seeing a placeholder block. Please wait while we or the broadcaster settle this.</desc>
    <category lang="en">General</category>
    <date>2026</date>
    <icon src="http://cable.fnswe.me/media/placeholder2.jpg" />
    <episode-num system="xmltv_ns">0.0.0/1</episode-num>
  </programme>
  <programme start="20260410050000 +0000" stop="20260410053000 +0000" channel="002">
    <title lang="en">No programme set</title>
    <desc lang="en">FBS teve has not set a programme block yet. Right now you are seeing a placeholder block. Please wait while we or the broadcaster settle this.</desc>
    <category lang="en">General</category>
    <date>2026</date>
    <icon src="http://cable.fnswe.me/media/placeholder2.jpg" />
    <episode-num system="xmltv_ns">0.0.0/1</episode-num>
  </programme>
  <programme start="20260410053000 +0000" stop="20260410060000 +0000" channel="002">
    <title lang="en">No programme set</title>
    <desc lang="en">FBS teve has not set a programme block yet. Right now you are seeing a placeholder block. Please wait while we or the broadcaster settle this.</desc>
    <category lang="en">General</category>
    <date>2026</date>
    <icon src="http://cable.fnswe.me/media/placeholder3.jpg" />
    <episode-num system="xmltv_ns">0.0.0/1</episode-num>
  </programme>
  <programme start="20260410060000 +0000" stop="20260410063000 +0000" channel="002">
    <title lang="en">No programme set</title>
    <desc lang="en">FBS teve has not set a programme block yet. Right now you are seeing a placeholder block. Please wait while we or the broadcaster settle this.</desc>
    <category lang="en">General</category>
    <date>2026</date>
    <icon src="http://cable.fnswe.me/media/placeholder3.jpg" />
    <episode-num system="xmltv_ns">0.0.0/1</episode-num>
  </programme>
  <programme start="20260410063000 +0000" stop="20260410070000 +0000" channel="002">
    <title lang="en">No programme set</title>
    <desc lang="en">FBS teve has not set a programme block yet. Right now you are seeing a placeholder block. Please wait while we or the broadcaster settle this.</desc>
    <category lang="en">General</category>
    <date>2026</date>
    <icon src="http://cable.fnswe.me/media/placeholder3.jpg" />
    <episode-num system="xmltv_ns">0.0.0/1</episode-num>
  </programme>
  <programme start="20260410070000 +0000" stop="20260410073000 +0000" channel="002">
    <title lang="en">No programme set</title>
    <desc lang="en">FBS teve has not set a programme block yet. Right now you are seeing a placeholder block. Please wait while we or the broadcaster settle this.</desc>
    <category lang="en">General</category>
    <date>2026</date>
    <icon src="http://cable.fnswe.me/media/placeholder3.jpg" />
    <episode-num system="xmltv_ns">0.0.0/1</episode-num>
  </programme>
  <programme start="20260410073000 +0000" stop="20260410080000 +0000" channel="002">
    <title lang="en">No programme set</title>
    <desc lang="en">FBS teve has not set a programme block yet. Right now you are seeing a placeholder block. Please wait while we or the broadcaster settle this.</desc>
    <category lang="en">General</category>
    <date>2026</date>
    <icon src="http://cable.fnswe.me/media/placeholder2.jpg" />
    <episode-num system="xmltv_ns">0.0.0/1</episode-num>
  </programme>
  <programme start="20260410080000 +0000" stop="20260410083000 +0000" channel="002">
    <title lang="en">No programme set</title>
    <desc lang="en">FBS teve has not set a programme block yet. Right now you are seeing a placeholder block. Please wait while we or the broadcaster settle this.</desc>
    <category lang="en">General</category>
    <date>2026</date>
    <icon src="http://cable.fnswe.me/media/placeholder2.jpg" />
    <episode-num system="xmltv_ns">0.0.0/1</episode-num>
  </programme>
  <programme start="20260410083000 +0000" stop="20260410090000 +0000" channel="002">
    <title lang="en">No programme set</title>
    <desc lang="en">FBS teve has not set a programme block yet. Right now you are seeing a placeholder block. Please wait while we or the broadcaster settle this.</desc>
    <category lang="en">General</category>
    <date>2026</date>
    <icon src="http://cable.fnswe.me/media/placeholder3.jpg" />
    <episode-num system="xmltv_ns">0.0.0/1</episode-num>
  </programme>
  <programme start="20260410090000 +0000" stop="20260410093000 +0000" channel="002">
    <title lang="en">No programme set</title>
    <desc lang="en">FBS teve has not set a programme block yet. Right now you are seeing a placeholder block. Please wait while we or the broadcaster settle this.</desc>
    <category lang="en">General</category>
    <date>2026</date>
    <icon src="http://cable.fnswe.me/media/placeholder2.jpg" />
    <episode-num system="xmltv_ns">0.0.0/1</episode-num>
  </programme>
  <programme start="20260410093000 +0000" stop="20260410100000 +0000" channel="002">
    <title lang="en">No programme set</title>
    <desc lang="en">FBS teve has not set a programme block yet. Right now you are seeing a placeholder block. Please wait while we or the broadcaster settle this.</desc>
    <category lang="en">General</category>
    <date>2026</date>
    <icon src="http://cable.fnswe.me/media/placeholder2.jpg" />
    <episode-num system="xmltv_ns">0.0.0/1</episode-num>
  </programme>
  <programme start="20260410100000 +0000" stop="20260410103000 +0000" channel="002">
    <title lang="en">No programme set</title>
    <desc lang="en">FBS teve has not set a programme block yet. Right now you are seeing a placeholder block. Please wait while we or the broadcaster settle this.</desc>
    <category lang="en">General</category>
    <date>2026</date>
    <icon src="http://cable.fnswe.me/media/placeholder1.jpg" />
    <episode-num system="xmltv_ns">0.0.0/1</episode-num>
  </programme>
  <programme start="20260410103000 +0000" stop="20260410110000 +0000" channel="002">
    <title lang="en">No programme set</title>
    <desc lang="en">FBS teve has not set a programme block yet. Right now you are seeing a placeholder block. Please wait while we or the broadcaster settle this.</desc>
    <category lang="en">General</category>
    <date>2026</date>
    <icon src="http://cable.fnswe.me/media/placeholder3.jpg" />
    <episode-num system="xmltv_ns">0.0.0/1</episode-num>
  </programme>
  <programme start="20260410110000 +0000" stop="20260410113000 +0000" channel="002">
    <title lang="en">No programme set</title>
    <desc lang="en">FBS teve has not set a programme block yet. Right now you are seeing a placeholder block. Please wait while we or the broadcaster settle this.</desc>
    <category lang="en">General</category>
    <date>2026</date>
    <icon src="http://cable.fnswe.me/media/placeholder2.jpg" />
    <episode-num system="xmltv_ns">0.0.0/1</episode-num>
  </programme>
  <programme start="20260410113000 +0000" stop="20260410120000 +0000" channel="002">
    <title lang="en">No programme set</title>
    <desc lang="en">FBS teve has not set a programme block yet. Right now you are seeing a placeholder block. Please wait while we or the broadcaster settle this.</desc>
    <category lang="en">General</category>
    <date>2026</date>
    <icon src="http://cable.fnswe.me/media/placeholder2.jpg" />
    <episode-num system="xmltv_ns">0.0.0/1</episode-num>
  </programme>
  <programme start="20260410120000 +0000" stop="20260410123000 +0000" channel="002">
    <title lang="en">No programme set</title>
    <desc lang="en">FBS teve has not set a programme block yet. Right now you are seeing a placeholder block. Please wait while we or the broadcaster settle this.</desc>
    <category lang="en">General</category>
    <date>2026</date>
    <icon src="http://cable.fnswe.me/media/placeholder2.jpg" />
    <episode-num system="xmltv_ns">0.0.0/1</episode-num>
  </programme>
  <programme start="20260410123000 +0000" stop="20260410130000 +0000" channel="002">
    <title lang="en">No programme set</title>
    <desc lang="en">FBS teve has not set a programme block yet. Right now you are seeing a placeholder block. Please wait while we or the broadcaster settle this.</desc>
    <category lang="en">General</category>
    <date>2026</date>
    <icon src="http://cable.fnswe.me/media/placeholder3.jpg" />
    <episode-num system="xmltv_ns">0.0.0/1</episode-num>
  </programme>
  <programme start="20260410130000 +0000" stop="20260410133000 +0000" channel="002">
    <title lang="en">No programme set</title>
    <desc lang="en">FBS teve has not set a programme block yet. Right now you are seeing a placeholder block. Please wait while we or the broadcaster settle this.</desc>
    <category lang="en">General</category>
    <date>2026</date>
    <icon src="http://cable.fnswe.me/media/placeholder3.jpg" />
    <episode-num system="xmltv_ns">0.0.0/1</episode-num>
  </programme>
  <programme start="20260410133000 +0000" stop="20260410140000 +0000" channel="002">
    <title lang="en">No programme set</title>
    <desc lang="en">FBS teve has not set a programme block yet. Right now you are seeing a placeholder block. Please wait while we or the broadcaster settle this.</desc>
    <category lang="en">General</category>
    <date>2026</date>
    <icon src="http://cable.fnswe.me/media/placeholder3.jpg" />
    <episode-num system="xmltv_ns">0.0.0/1</episode-num>
  </programme>
  <programme start="20260410140000 +0000" stop="20260410143000 +0000" channel="002">
    <title lang="en">No programme set</title>
    <desc lang="en">FBS teve has not set a programme block yet. Right now you are seeing a placeholder block. Please wait while we or the broadcaster settle this.</desc>
    <category lang="en">General</category>
    <date>2026</date>
    <icon src="http://cable.fnswe.me/media/placeholder2.jpg" />
    <episode-num system="xmltv_ns">0.0.0/1</episode-num>
  </programme>
  <programme start="20260410143000 +0000" stop="20260410150000 +0000" channel="002">
    <title lang="en">No programme set</title>
    <desc lang="en">FBS teve has not set a programme block yet. Right now you are seeing a placeholder block. Please wait while we or the broadcaster settle this.</desc>
    <category lang="en">General</category>
    <date>2026</date>
    <icon src="http://cable.fnswe.me/media/placeholder1.jpg" />
    <episode-num system="xmltv_ns">0.0.0/1</episode-num>
  </programme>
  <programme start="20260410150000 +0000" stop="20260410153000 +0000" channel="002">
    <title lang="en">No programme set</title>
    <desc lang="en">FBS teve has not set a programme block yet. Right now you are seeing a placeholder block. Please wait while we or the broadcaster settle this.</desc>
    <category lang="en">General</category>
    <date>2026</date>
    <icon src="http://cable.fnswe.me/media/placeholder1.jpg" />
    <episode-num system="xmltv_ns">0.0.0/1</episode-num>
  </programme>
  <programme start="20260410153000 +0000" stop="20260410160000 +0000" channel="002">
    <title lang="en">No programme set</title>
    <desc lang="en">FBS teve has not set a programme block yet. Right now you are seeing a placeholder block. Please wait while we or the broadcaster settle this.</desc>
    <category lang="en">General</category>
    <date>2026</date>
    <icon src="http://cable.fnswe.me/media/placeholder3.jpg" />
    <episode-num system="xmltv_ns">0.0.0/1</episode-num>
  </programme>
  <programme start="20260410160000 +0000" stop="20260410163000 +0000" channel="002">
    <title lang="en">No programme set</title>
    <desc lang="en">FBS teve has not set a programme block yet. Right now you are seeing a placeholder block. Please wait while we or the broadcaster settle this.</desc>
    <category lang="en">General</category>
    <date>2026</date>
    <icon src="http://cable.fnswe.me/media/placeholder2.jpg" />
    <episode-num system="xmltv_ns">0.0.0/1</episode-num>
  </programme>
  <programme start="20260410163000 +0000" stop="20260410170000 +0000" channel="002">
    <title lang="en">No programme set</title>
    <desc lang="en">FBS teve has not set a programme block yet. Right now you are seeing a placeholder block. Please wait while we or the broadcaster settle this.</desc>
    <category lang="en">General</category>
    <date>2026</date>
    <icon src="http://cable.fnswe.me/media/placeholder2.jpg" />
    <episode-num system="xmltv_ns">0.0.0/1</episode-num>
  </programme>
  <programme start="20260410170000 +0000" stop="20260410173000 +0000" channel="002">
    <title lang="en">No programme set</title>
    <desc lang="en">FBS teve has not set a programme block yet. Right now you are seeing a placeholder block. Please wait while we or the broadcaster settle this.</desc>
    <category lang="en">General</category>
    <date>2026</date>
    <icon src="http://cable.fnswe.me/media/placeholder1.jpg" />
    <episode-num system="xmltv_ns">0.0.0/1</episode-num>
  </programme>
  <programme start="20260410173000 +0000" stop="20260410180000 +0000" channel="002">
    <title lang="en">No programme set</title>
    <desc lang="en">FBS teve has not set a programme block yet. Right now you are seeing a placeholder block. Please wait while we or the broadcaster settle this.</desc>
    <category lang="en">General</category>
    <date>2026</date>
    <icon src="http://cable.fnswe.me/media/placeholder2.jpg" />
    <episode-num system="xmltv_ns">0.0.0/1</episode-num>
  </programme>
  <programme start="20260410180000 +0000" stop="20260410183000 +0000" channel="002">
    <title lang="en">No programme set</title>
    <desc lang="en">FBS teve has not set a programme block yet. Right now you are seeing a placeholder block. Please wait while we or the broadcaster settle this.</desc>
    <category lang="en">General</category>
    <date>2026</date>
    <icon src="http://cable.fnswe.me/media/placeholder2.jpg" />
    <episode-num system="xmltv_ns">0.0.0/1</episode-num>
  </programme>
  <programme start="20260410183000 +0000" stop="20260410190000 +0000" channel="002">
    <title lang="en">No programme set</title>
    <desc lang="en">FBS teve has not set a programme block yet. Right now you are seeing a placeholder block. Please wait while we or the broadcaster settle this.</desc>
    <category lang="en">General</category>
    <date>2026</date>
    <icon src="http://cable.fnswe.me/media/placeholder3.jpg" />
    <episode-num system="xmltv_ns">0.0.0/1</episode-num>
  </programme>
  <programme start="20260410190000 +0000" stop="20260410193000 +0000" channel="002">
    <title lang="en">No programme set</title>
    <desc lang="en">FBS teve has not set a programme block yet. Right now you are seeing a placeholder block. Please wait while we or the broadcaster settle this.</desc>
    <category lang="en">General</category>
    <date>2026</date>
    <icon src="http://cable.fnswe.me/media/placeholder3.jpg" />
    <episode-num system="xmltv_ns">0.0.0/1</episode-num>
  </programme>
  <programme start="20260410193000 +0000" stop="20260410200000 +0000" channel="002">
    <title lang="en">No programme set</title>
    <desc lang="en">FBS teve has not set a programme block yet. Right now you are seeing a placeholder block. Please wait while we or the broadcaster settle this.</desc>
    <category lang="en">General</category>
    <date>2026</date>
    <icon src="http://cable.fnswe.me/media/placeholder1.jpg" />
    <episode-num system="xmltv_ns">0.0.0/1</episode-num>
  </programme>
  <programme start="20260410200000 +0000" stop="20260410203000 +0000" channel="002">
    <title lang="en">No programme set</title>
    <desc lang="en">FBS teve has not set a programme block yet. Right now you are seeing a placeholder block. Please wait while we or the broadcaster settle this.</desc>
    <category lang="en">General</category>
    <date>2026</date>
    <icon src="http://cable.fnswe.me/media/placeholder2.jpg" />
    <episode-num system="xmltv_ns">0.0.0/1</episode-num>
  </programme>
  <programme start="20260410203000 +0000" stop="20260410210000 +0000" channel="002">
    <title lang="en">No programme set</title>
    <desc lang="en">FBS teve has not set a programme block yet. Right now you are seeing a placeholder block. Please wait while we or the broadcaster settle this.</desc>
    <category lang="en">General</category>
    <date>2026</date>
    <icon src="http://cable.fnswe.me/media/placeholder3.jpg" />
    <episode-num system="xmltv_ns">0.0.0/1</episode-num>
  </programme>
  <programme start="20260410210000 +0000" stop="20260410213000 +0000" channel="002">
    <title lang="en">No programme set</title>
    <desc lang="en">FBS teve has not set a programme block yet. Right now you are seeing a placeholder block. Please wait while we or the broadcaster settle this.</desc>
    <category lang="en">General</category>
    <date>2026</date>
    <icon src="http://cable.fnswe.me/media/placeholder3.jpg" />
    <episode-num system="xmltv_ns">0.0.0/1</episode-num>
  </programme>
  <programme start="20260410213000 +0000" stop="20260410220000 +0000" channel="002">
    <title lang="en">No programme set</title>
    <desc lang="en">FBS teve has not set a programme block yet. Right now you are seeing a placeholder block. Please wait while we or the broadcaster settle this.</desc>
    <category lang="en">General</category>
    <date>2026</date>
    <icon src="http://cable.fnswe.me/media/placeholder3.jpg" />
    <episode-num system="xmltv_ns">0.0.0/1</episode-num>
  </programme>
  <programme start="20260410220000 +0000" stop="20260410223000 +0000" channel="002">
    <title lang="en">No programme set</title>
    <desc lang="en">FBS teve has not set a programme block yet. Right now you are seeing a placeholder block. Please wait while we or the broadcaster settle this.</desc>
    <category lang="en">General</category>
    <date>2026</date>
    <icon src="http://cable.fnswe.me/media/placeholder3.jpg" />
    <episode-num system="xmltv_ns">0.0.0/1</episode-num>
  </programme>
  <programme start="20260410223000 +0000" stop="20260410230000 +0000" channel="002">
    <title lang="en">No programme set</title>
    <desc lang="en">FBS teve has not set a programme block yet. Right now you are seeing a placeholder block. Please wait while we or the broadcaster settle this.</desc>
    <category lang="en">General</category>
    <date>2026</date>
    <icon src="http://cable.fnswe.me/media/placeholder3.jpg" />
    <episode-num system="xmltv_ns">0.0.0/1</episode-num>
  </programme>
  <programme start="20260410230000 +0000" stop="20260410233000 +0000" channel="002">
    <title lang="en">No programme set</title>
    <desc lang="en">FBS teve has not set a programme block yet. Right now you are seeing a placeholder block. Please wait while we or the broadcaster settle this.</desc>
    <category lang="en">General</category>
    <date>2026</date>
    <icon src="http://cable.fnswe.me/media/placeholder2.jpg" />
    <episode-num system="xmltv_ns">0.0.0/1</episode-num>
  </programme>
  <programme start="20260410233000 +0000" stop="20260411000000 +0000" channel="002">
    <title lang="en">No programme set</title>
    <desc lang="en">FBS teve has not set a programme block yet. Right now you are seeing a placeholder block. Please wait while we or the broadcaster settle this.</desc>
    <category lang="en">General</category>
    <date>2026</date>
    <icon src="http://cable.fnswe.me/media/placeholder2.jpg" />
    <episode-num system="xmltv_ns">0.0.0/1</episode-num>
  </programme>
  <programme start="20260410000000 +0000" stop="20260411000000 +0000" channel="003">
    <title lang="en">No programme set</title>
    <desc lang="en">No TV channel has not set a programme block yet. Right now you are seeing a placeholder block. Please wait while we or the broadcaster settle this.</desc>
    <category lang="en">General</category>
    <date>2026</date>
    <icon src="http://cable.fnswe.me/media/placeholder1.jpg" />
    <episode-num system="xmltv_ns">0.0.0/1</episode-num>
  </programme>
</tv>